CHANGES.rst
LICENSE
MANIFEST.in
README.md
bootstrap.py
buildout.cfg
setup.py
collective/__init__.py
collective.stripe.egg-info/PKG-INFO
collective.stripe.egg-info/SOURCES.txt
collective.stripe.egg-info/dependency_links.txt
collective.stripe.egg-info/entry_points.txt
collective.stripe.egg-info/namespace_packages.txt
collective.stripe.egg-info/not-zip-safe
collective.stripe.egg-info/requires.txt
collective.stripe.egg-info/top_level.txt
collective/stripe/__init__.py
collective/stripe/configure.zcml
collective/stripe/controlpanel.py
collective/stripe/interfaces.py
collective/stripe/stripe_token_input.pt
collective/stripe/testing.py
collective/stripe/utils.py
collective/stripe/viewlets.py
collective/stripe/vocabularies.py
collective/stripe/webhooks.py
collective/stripe/widgets.py
collective/stripe/locales/README.txt
collective/stripe/profiles/default/controlpanel.xml
collective/stripe/profiles/default/jsregistry.xml
collective/stripe/profiles/default/metadata.xml
collective/stripe/profiles/default/registry.xml
collective/stripe/static/README.txt
collective/stripe/tests/__init__.py
collective/stripe/tests/dummy_stripe.py
collective/stripe/tests/test_controlpanel.py
collective/stripe/tests/test_utils.py