Metadata-Version: 1.1
Name: collective.stripe
Version: 0.3.2
Summary: Stripe Credit Card Processing Integration
Home-page: http://github/collective/collective.stripe
Author: UNKNOWN
Author-email: UNKNOWN
License: GPL
Platform: UNKNOWN
Classifier: Framework :: Plone
Classifier: Programming Language :: Python
Classifier: Topic :: Software Development :: Libraries :: Python Modules
